trellis_topo/__init__.py
trellis_topo/bmv2.py
trellis_topo/gen_link_config.py
trellis_topo/gen_trellis_config.py
trellis_topo/routinglib.py
trellis_topo/trellisp4.py
trellis_topo-0.0.2.dist-info/METADATA
trellis_topo-0.0.2.dist-info/RECORD
trellis_topo-0.0.2.dist-info/WHEEL
trellis_topo-0.0.2.dist-info/top_level.txt
