Metadata-Version: 2.1
Name: trellis-topo
Version: 0.0.2
Summary: Mininet script to create leaf-spine structure
Home-page: UNKNOWN
License: UNKNOWN
Platform: UNKNOWN
Classifier: Programming Language :: Python :: 2
Classifier: License :: OSI Approved :: MIT License
Classifier: Operating System :: OS Independent
